tests/__init__.py
tests/test_converter.py
vw2px/__init__.py
vw2px/__main__.py
vw2px/converter.py
vw2px-1.0.0.dist-info/licenses/LICENSE
vw2px-1.0.0.dist-info/METADATA
vw2px-1.0.0.dist-info/WHEEL
vw2px-1.0.0.dist-info/entry_points.txt
vw2px-1.0.0.dist-info/top_level.txt
vw2px-1.0.0.dist-info/RECORD
