Metadata-Version: 2.4
Name: vw2px
Version: 1.0.0
Summary: Конвертер размеров из VW в PX для проектов Vue, React, Next.js и других веб-проектов
Home-page: https://github.com/Bluesuma/vw2px
Author: Bluesuma
Author-email: Bluesuma <v1tuze@yandex.ru>
Maintainer-email: Bluesuma <v1tuze@yandex.ru>
License: MIT
Project-URL: Homepage, https://github.com/Bluesuma/vw2px
Project-URL: Documentation, https://github.com/Bluesuma/vw2px#readme
Project-URL: Repository, https://github.com/Bluesuma/vw2px
Project-URL: Bug Tracker, https://github.com/Bluesuma/vw2px/issues
Keywords: vw,px,converter,css,vue,react,nextjs,web,development,frontend
Platform: any
Classifier: Development Status :: 5 - Production/Stable
Classifier: Intended Audience :: Developers
Classifier: Topic :: Software Development :: Build Tools
Classifier: Topic :: Software Development :: Libraries :: Python Modules
Classifier: License :: OSI Approved :: MIT License
Classifier: Programming Language :: Python :: 3
Classifier: Programming Language :: Python :: 3.7
Classifier: Programming Language :: Python :: 3.8
Classifier: Programming Language :: Python :: 3.9
Classifier: Programming Language :: Python :: 3.10
Classifier: Programming Language :: Python :: 3.11
Classifier: Programming Language :: Python :: 3.12
Classifier: Operating System :: OS Independent
Classifier: Environment :: Console
Requires-Python: >=3.7
License-File: LICENSE
Requires-Dist: click>=8.0.0
Requires-Dist: colorama>=0.4.0
Provides-Extra: dev
Requires-Dist: pytest>=6.0; extra == "dev"
Requires-Dist: pytest-cov>=2.0; extra == "dev"
Requires-Dist: black>=21.0; extra == "dev"
Requires-Dist: flake8>=3.8; extra == "dev"
Requires-Dist: mypy>=0.800; extra == "dev"
Requires-Dist: pre-commit>=2.0; extra == "dev"
Dynamic: author
Dynamic: home-page
Dynamic: license-file
Dynamic: platform
Dynamic: requires-python
